space_filling_pytorch/__init__.py
space_filling_pytorch-0.0.5.dist-info/LICENSE
space_filling_pytorch-0.0.5.dist-info/METADATA
space_filling_pytorch-0.0.5.dist-info/WHEEL
space_filling_pytorch-0.0.5.dist-info/top_level.txt
space_filling_pytorch-0.0.5.dist-info/RECORD
