Metadata-Version: 2.1
Name: space-filling-pytorch
Version: 0.0.5
Summary: A set of pytorch implementations for space filling curve using OpenAI Triton
Home-page: https://github.com/Kitsunetic/space-filling-pytorch
Author: Kitsunetic
Author-email: jh.shim.gg@gmail.com
License: UNKNOWN
Platform: UNKNOWN
License-File: LICENSE
Requires-Dist: torch
Requires-Dist: triton
